tbot223_core/AppCore.py
tbot223_core/Exception.py
tbot223_core/FileManager.py
tbot223_core/LogSys.py
tbot223_core/Result.py
tbot223_core/Utils.py
tbot223_core/__init__.py
tbot223_core-2.0.9.dist-info/licenses/LICENSE
tbot223_core-2.0.9.dist-info/METADATA
tbot223_core-2.0.9.dist-info/WHEEL
tbot223_core-2.0.9.dist-info/top_level.txt
tbot223_core-2.0.9.dist-info/RECORD
