Metadata-Version: 2.4
Name: tbot223-core
Version: 2.0.9
Summary: A core utility package for tbot223 projects.
Home-page: https://github.com/Tbot223/Core
Author: tbot223
Author-email: tbotxyz@gmail.com
Keywords: pypi,package,utilities,python,tbot223
Classifier: Programming Language :: Python :: 3.10
Classifier: Programming Language :: Python :: 3.11
Classifier: Programming Language :: Python :: 3.12
Classifier: License :: OSI Approved :: Apache Software License
Requires-Python: >=3.10
License-File: LICENSE
Dynamic: author
Dynamic: author-email
Dynamic: classifier
Dynamic: description
Dynamic: description-content-type
Dynamic: home-page
Dynamic: keywords
Dynamic: license-file
Dynamic: requires-python
Dynamic: summary
